{
	"name": "MENU PRINCIPAL",
	"layers": [
		{
			"name": "Capa 0",
			"overriden": 0,
			"subLayers": [],
			"instances": [
				{
					"type": "FondoEnMosaico2",
					"properties": {
						"initially-visible": true,
						"origin": "top-left",
						"wrap-horizontal": "repeat",
						"wrap-vertical": "repeat",
						"image-offset-x": 0,
						"image-offset-y": 0,
						"image-scale-x": 1,
						"image-scale-y": 1,
						"image-angle": 0,
						"enable-tile-randomization": false,
						"x-random": 1,
						"y-random": 1,
						"angle-random": 1,
						"blend-margin-x": 0.1,
						"blend-margin-y": 0.1
					},
					"uid": 23,
					"instanceVariables": {},
					"behaviors": {},
					"world": {
						"x": -168,
						"y": -146,
						"width": 2368,
						"height": 1408,
						"originX": 0,
						"originY": 0,
						"color": [
							1,
							1,
							1,
							1
						],
						"angle": 0,
						"zElevation": 0
					}
				},
				{
					"type": "BACKGROUNDETESC1",
					"properties": {
						"initially-visible": true,
						"initial-animation": "Animation 1",
						"initial-frame": 0,
						"enable-collisions": true,
						"live-preview": false
					},
					"uid": 8,
					"instanceVariables": {},
					"behaviors": {},
					"world": {
						"x": 211,
						"y": 666,
						"width": 1086.3580256871599,
						"height": 1248.1560295129075,
						"originX": -0.7021276595744681,
						"originY": 0.6185185185185185,
						"color": [
							1,
							1,
							1,
							1
						],
						"angle": 0,
						"zElevation": 0
					}
				},
				{
					"type": "PICI",
					"properties": {
						"initially-visible": true,
						"initial-animation": "Animation 1",
						"initial-frame": 0,
						"enable-collisions": true,
						"live-preview": false
					},
					"uid": 7,
					"instanceVariables": {},
					"behaviors": {},
					"world": {
						"x": 618.2173705131363,
						"y": 584.9378341955646,
						"width": 1072.7813903697793,
						"height": 859.8144180593343,
						"originX": 0.47555555555555556,
						"originY": 0.4048059149722736,
						"color": [
							1,
							1,
							1,
							1
						],
						"angle": 0,
						"zElevation": 0
					}
				},
				{
					"type": "TITULOJUEGO",
					"properties": {
						"initially-visible": true,
						"initial-animation": "Animation 1",
						"initial-frame": 0,
						"enable-collisions": true,
						"live-preview": false
					},
					"uid": 21,
					"instanceVariables": {},
					"behaviors": {},
					"world": {
						"x": 339,
						"y": -93,
						"width": 836.2415918859813,
						"height": 189.54809416082242,
						"originX": 0.35333333333333333,
						"originY": -0.9215686274509803,
						"color": [
							1,
							1,
							1,
							1
						],
						"angle": 0,
						"zElevation": 0
					}
				},
				{
					"type": "CARPETA",
					"properties": {
						"initially-visible": true,
						"initial-animation": "Animation 1",
						"initial-frame": 0,
						"enable-collisions": true,
						"live-preview": false
					},
					"uid": 11,
					"instanceVariables": {},
					"behaviors": {},
					"world": {
						"x": 1680,
						"y": 353,
						"width": 255.1470164434615,
						"height": 200.47265577700543,
						"originX": 0.5204081632653061,
						"originY": 0.5324675324675324,
						"color": [
							1,
							1,
							1,
							1
						],
						"angle": 0,
						"zElevation": 0
					}
				},
				{
					"type": "CARPETA",
					"properties": {
						"initially-visible": true,
						"initial-animation": "Animation 1",
						"initial-frame": 0,
						"enable-collisions": true,
						"live-preview": false
					},
					"uid": 18,
					"instanceVariables": {},
					"behaviors": {},
					"world": {
						"x": 1676,
						"y": 614,
						"width": 255.1470164434615,
						"height": 200.47265577700543,
						"originX": 0.5204081632653061,
						"originY": 0.5324675324675324,
						"color": [
							1,
							1,
							1,
							1
						],
						"angle": 0,
						"zElevation": 0
					}
				},
				{
					"type": "TextoEmpezar",
					"properties": {
						"text": "¡Empezar!",
						"enable-bbcode": true,
						"font": "monospace",
						"size": 32,
						"line-height": 0,
						"bold": false,
						"italic": false,
						"color": [
							0,
							0,
							0,
							1
						],
						"horizontal-alignment": "left",
						"vertical-alignment": "top",
						"wrapping": "word",
						"initially-visible": true,
						"origin": "top-left",
						"read-aloud": false
					},
					"uid": 30,
					"instanceVariables": {},
					"behaviors": {},
					"world": {
						"x": 1572,
						"y": 449,
						"width": 254,
						"height": 84,
						"originX": 0,
						"originY": 0,
						"color": [
							1,
							1,
							1,
							1
						],
						"angle": 0,
						"zElevation": 0
					}
				},
				{
					"type": "PICICARA",
					"properties": {
						"initially-visible": true,
						"initial-animation": "Animation 1",
						"initial-frame": 0,
						"enable-collisions": true,
						"live-preview": false
					},
					"uid": 31,
					"instanceVariables": {},
					"behaviors": {
						"Desvanecer": {
							"properties": {
								"fade-in-time": 10,
								"wait-time": 0,
								"fade-out-time": 0,
								"destroy": false,
								"enabled": true,
								"live-preview": false
							}
						}
					},
					"world": {
						"x": 598,
						"y": 541,
						"width": 499.5561666483195,
						"height": 274.7558916565758,
						"originX": 0.505,
						"originY": 0.5181818181818182,
						"color": [
							1,
							1,
							1,
							1
						],
						"angle": 0,
						"zElevation": 0
					}
				},
				{
					"type": "FondoEnMosaico3",
					"properties": {
						"initially-visible": true,
						"origin": "top-left",
						"wrap-horizontal": "repeat",
						"wrap-vertical": "repeat",
						"image-offset-x": 0,
						"image-offset-y": 0,
						"image-scale-x": 1,
						"image-scale-y": 1,
						"image-angle": 0,
						"enable-tile-randomization": false,
						"x-random": 1,
						"y-random": 1,
						"angle-random": 1,
						"blend-margin-x": 0.1,
						"blend-margin-y": 0.1
					},
					"uid": 32,
					"instanceVariables": {},
					"behaviors": {
						"Desvanecer": {
							"properties": {
								"fade-in-time": 0,
								"wait-time": 0,
								"fade-out-time": 1,
								"destroy": true,
								"enabled": true,
								"live-preview": false
							}
						}
					},
					"world": {
						"x": 1977,
						"y": 27,
						"width": 1967,
						"height": 1140,
						"originX": 0,
						"originY": 0,
						"color": [
							1,
							1,
							1,
							1
						],
						"angle": 0,
						"zElevation": 0
					}
				}
			],
			"sid": 771836694456463,
			"effectTypes": [],
			"isInitiallyVisible": true,
			"isInitiallyInteractive": true,
			"color": [
				1,
				1,
				1,
				1
			],
			"backgroundColor": [
				0.3686274509803922,
				0.3686274509803922,
				0.3686274509803922,
				1
			],
			"isTransparent": false,
			"parallaxX": 1,
			"parallaxY": 1,
			"scaleRate": 1,
			"forceOwnTexture": false,
			"renderingMode": "3d",
			"drawOrder": "z-order",
			"useRenderCells": false,
			"blendMode": "normal",
			"zElevation": 0,
			"global": false
		}
	],
	"sid": 306583214707330,
	"nonworld-instances": [],
	"effectTypes": [],
	"width": 1920,
	"height": 1080,
	"unboundedScrolling": false,
	"vpX": 0.5,
	"vpY": 0.5,
	"projection": "perspective",
	"eventSheet": "EVENTOS MENU PRINCIPAL"
}