{
	"name": "BOTONM2",
	"plugin-id": "Sprite",
	"sid": 276265848556779,
	"isGlobal": false,
	"instanceVariables": [
		{
			"name": "OpcionActiva",
			"type": "boolean",
			"desc": "",
			"show": true,
			"sid": 246320533343571
		}
	],
	"behaviorTypes": [],
	"effectTypes": [],
	"animations": {
		"items": [
			{
				"frames": [
					{
						"width": 208,
						"height": 63,
						"originX": 0.5192307692307693,
						"originY": 0.49206349206349204,
						"originalSource": "",
						"exportFormat": "lossless",
						"exportQuality": 0.8,
						"imageSpriteId": 4619263,
						"collisionPoly": {
							"points": [
								0,
								0,
								0,
								0,
								1,
								0,
								0.9903846153846154,
								0.18253968253968253,
								1,
								1,
								0,
								1,
								0,
								1,
								0,
								0.18253968253968253
							]
						},
						"useCollisionPoly": true,
						"duration": 1
					}
				],
				"sid": 206249602567837,
				"name": "Animation 1",
				"isLooping": false,
				"isPingPong": false,
				"repeatCount": 1,
				"repeatTo": 0,
				"speed": 5
			}
		],
		"subfolders": []
	}
}